{"cameraMode":{"drawMode":0,"name":"Shaded","section":"Shading Mode"},"sceneLighting":true,"audioPlay":false,"sceneViewState":{"showFog":true,"showMaterialUpdate":false,"showSkybox":true,"showFlares":true,"showImageEffects":true,"showParticleSystems":true,"showVisualEffectGraphs":true,"m_FxEnabled":true},"in2DMode":false,"pivot":{"x":0.0,"y":0.0,"z":-2.5},"rotation":{"x":0.08859989047050476,"y":-0.16741615533828736,"z":0.015108386985957623,"w":0.9817824363708496},"size":17.41609001159668,"orthographic":true}