{"cameraMode":{"drawMode":0,"name":"Shaded","section":"Shading Mode"},"sceneLighting":false,"audioPlay":false,"sceneViewState":{"showFog":true,"showMaterialUpdate":false,"showSkybox":false,"showFlares":true,"showImageEffects":true,"showParticleSystems":true,"showVisualEffectGraphs":true,"m_FxEnabled":true},"in2DMode":false,"pivot":{"x":11.804157257080079,"y":4.909999847412109,"z":17.320045471191408},"rotation":{"x":0.1391928791999817,"y":-0.5420308113098145,"z":0.09158877283334732,"w":0.8237138390541077},"size":57.459373474121097,"orthographic":true}